MANIFEST.in
Makefile
README
setup.py
hgsubversion/__init__.py
hgsubversion/__version__.py
hgsubversion/compathacks.py
hgsubversion/editor.py
hgsubversion/maps.py
hgsubversion/pushmod.py
hgsubversion/replay.py
hgsubversion/stupid.py
hgsubversion/svncommands.py
hgsubversion/svnexternals.py
hgsubversion/svnmeta.py
hgsubversion/svnrepo.py
hgsubversion/util.py
hgsubversion/verify.py
hgsubversion/wrappers.py
hgsubversion.egg-info/PKG-INFO
hgsubversion.egg-info/SOURCES.txt
hgsubversion.egg-info/dependency_links.txt
hgsubversion.egg-info/requires.txt
hgsubversion.egg-info/top_level.txt
hgsubversion/help/subversion.rst
hgsubversion/hooks/__init__.py
hgsubversion/hooks/updatemeta.py
hgsubversion/layouts/__init__.py
hgsubversion/layouts/base.py
hgsubversion/layouts/custom.py
hgsubversion/layouts/single.py
hgsubversion/layouts/standard.py
hgsubversion/svnwrap/__init__.py
hgsubversion/svnwrap/common.py
hgsubversion/svnwrap/subvertpy_wrapper.py
hgsubversion/svnwrap/svn_swig_wrapper.py
tests/run.py
tests/test_binaryfiles.py
tests/test_diff.py
tests/test_externals.py
tests/test_fetch_branches.py
tests/test_fetch_command.py
tests/test_fetch_command_regexes.py
tests/test_fetch_dir_removal.py
tests/test_fetch_exec.py
tests/test_fetch_mappings.py
tests/test_fetch_renames.py
tests/test_fetch_symlinks.py
tests/test_fetch_truncated.py
tests/test_helpers.py
tests/test_hooks.py
tests/test_pull.py
tests/test_pull_fallback.py
tests/test_push_autoprops.py
tests/test_push_command.py
tests/test_push_dirs.py
tests/test_push_eol.py
tests/test_push_renames.py
tests/test_revmap_migrate.py
tests/test_single_dir_clone.py
tests/test_single_dir_push.py
tests/test_svn_pre_commit_hooks.py
tests/test_svnwrap.py
tests/test_tags.py
tests/test_template_keywords.py
tests/test_unaffected_core.py
tests/test_urls.py
tests/test_util.py
tests/test_utility_commands.py
tests/comprehensive/test_custom_layout.py
tests/comprehensive/test_obsstore_on.py
tests/comprehensive/test_rebuildmeta.py
tests/comprehensive/test_sqlite_revmap.py
tests/comprehensive/test_stupid_pull.py
tests/comprehensive/test_updatemeta.py
tests/comprehensive/test_verify_and_startrev.py
tests/fixtures/addspecial.sh
