Metadata-Version: 1.1
Name: hgsubversion
Version: 1.9.1
Summary: hgsubversion is a Mercurial extension for working with Subversion repositories.
Home-page: http://bitbucket.org/durin42/hgsubversion
Author: Augie Fackler, others
Author-email: durin42@gmail.com
License: GNU GPL
Keywords: mercurial
Platform: any
Classifier: License :: OSI Approved :: GNU General Public License (GPL)
Classifier: Intended Audience :: Developers
Classifier: Topic :: Software Development :: Version Control
Classifier: Development Status :: 4 - Beta
Classifier: Programming Language :: Python
Classifier: Operating System :: OS Independent
